nuttssh/__init__.py
nuttssh/__main__.py
nuttssh/commands.py
nuttssh/server.py
nuttssh/util.py
nuttssh-0.3.dist-info/LICENSE
nuttssh-0.3.dist-info/METADATA
nuttssh-0.3.dist-info/WHEEL
nuttssh-0.3.dist-info/RECORD
