Metadata-Version: 2.1
Name: nuttssh
Version: 0.3
Summary: SSH switchboard for internally patching forwarded ports
Home-page: http://github.com/matthijskooijman/nuttssh
License: MIT
Author: Matthijs Kooijman
Author-email: matthijs@stdin.nl
Requires-Python: >=3.5,<4.0
Classifier: Development Status :: 3 - Alpha
Classifier: Environment :: No Input/Output (Daemon)
Classifier: Framework :: AsyncIO
Classifier: License :: OSI Approved :: MIT License
Classifier: Programming Language :: Python :: 3
Classifier: Programming Language :: Python :: 3.5
Classifier: Programming Language :: Python :: 3.6
Classifier: Programming Language :: Python :: 3.7
Classifier: Programming Language :: Python :: 3.8
Classifier: Programming Language :: Python :: 3.9
Classifier: Programming Language :: Python :: 3.10
Classifier: Programming Language :: Python :: 3.11
Classifier: Programming Language :: Python :: 3 :: Only
Classifier: Topic :: Internet :: Proxy Servers
Classifier: Topic :: System :: Networking
Requires-Dist: asyncssh (>=2.3,<3.0)
Project-URL: Repository, http://github.com/matthijskooijman/nuttssh
